Metadata-Version: 2.4
Name: web.py-update
Version: 0.75.1
Summary: web.py: makes web apps
Author-email: Aaron Swartz <me@aaronsw.com>
Maintainer-email: Anand Chitipothu <anandology@gmail.com>
License: Public domain
Project-URL: Homepage, http://webpy.org/
Project-URL: Source, https://github.com/webpy/webpy
Platform: any
Classifier: License :: Public Domain
Classifier: Programming Language :: Python
Classifier: Programming Language :: Python :: 3 :: Only
Classifier: Programming Language :: Python :: 3.8
Classifier: Programming Language :: Python :: 3.9
Classifier: Programming Language :: Python :: 3.10
Classifier: Programming Language :: Python :: 3.11
Classifier: Programming Language :: Python :: 3.12
Classifier: Programming Language :: Python :: 3.13
Classifier: Programming Language :: Python :: 3.14
Requires-Python: <3.15,>=3.8
License-File: LICENSE.txt
Requires-Dist: cheroot>=6.0.0
Requires-Dist: more_itertools>=2.6
Requires-Dist: multipart>=0.2.4
Dynamic: license-file
